shroudstone/__init__.py
shroudstone/__main__.py
shroudstone/cli.py
shroudstone/config.py
shroudstone/logging.py
shroudstone/renamer.py
shroudstone/gui/__init__.py
shroudstone/gui/__main__.py
shroudstone/gui/app.py
shroudstone/gui/fonts.py
shroudstone/gui/jobs.py
shroudstone/gui/logview.py
shroudstone/gui/assets/shroudstone.ico
shroudstone/gui/assets/shroudstone.png
shroudstone/gui/assets/shroudstone.svg
shroudstone/replay/parser.py
shroudstone/replay/stormgate_pb2.py
shroudstone/replay/stormgate_pb2.pyi
shroudstone/replay/summary.py
shroudstone/replay/versions.py
shroudstone-0.2.8.dist-info/entry_points.txt
shroudstone-0.2.8.dist-info/licenses/LICENSE
shroudstone-0.2.8.dist-info/WHEEL
shroudstone-0.2.8.dist-info/METADATA
shroudstone-0.2.8.dist-info/RECORD
