Metadata-Version: 2.4
Name: shroudstone
Version: 0.2.8
Summary: Python utilities for working with Stormgate replays
Keywords: Stormgate
Author-email: Anthony Carapetis <anthony.carapetis@gmail.com>
Requires-Python: >=3.8,<4
Classifier: License :: OSI Approved :: GNU General Public License v3 or later (GPLv3+)
Classifier: Topic :: Games/Entertainment :: Real Time Strategy
License-File: LICENSE
Requires-Dist: packaging>=20.4
Requires-Dist: pillow>=5.0
Requires-Dist: protobuf~=5.27.3
Requires-Dist: pydantic~=2.6
Requires-Dist: pystray~=0.19.5
Requires-Dist: python-dateutil>=2.8.2
Requires-Dist: pyyaml>=5
Requires-Dist: typer[all]~=0.9.0
Requires-Dist: typing_extensions>=4.7.1
Requires-Dist: pytest>=8 ; extra == "test"
Requires-Dist: tzdata ; extra == "test" and ( sys_platform == 'win32')
Project-URL: Source, https://github.com/acarapetis/shroudstone
Provides-Extra: test
